torchcross/__init__.py
torchcross/cd/__init__.py
torchcross/cd/activations.py
torchcross/cd/losses.py
torchcross/cd/heads/__init__.py
torchcross/cd/heads/classification.py
torchcross/cd/metrics/__init__.py
torchcross/cd/metrics/classification.py
torchcross/cd/metrics/wrappers.py
torchcross/data/__init__.py
torchcross/data/dataset.py
torchcross/data/task.py
torchcross/data/task_source.py
torchcross/data/metadataset/__init__.py
torchcross/data/metadataset/base.py
torchcross/data/metadataset/collection.py
torchcross/data/metadataset/few_shot.py
torchcross/data/metadataset/few_shot_dummies.py
torchcross/models/__init__.py
torchcross/models/cross_domain.py
torchcross/models/episodic.py
torchcross/models/maml.py
torchcross/models/protonet.py
torchcross/models/simple.py
torchcross/models/lightning/__init__.py
torchcross/models/lightning/cross_domain.py
torchcross/models/lightning/cross_domain_classifier.py
torchcross/models/lightning/episodic.py
torchcross/models/lightning/maml.py
torchcross/models/lightning/mixins.py
torchcross/models/lightning/protonet.py
torchcross/models/lightning/simple.py
torchcross/utils/__init__.py
torchcross/utils/collate_fn.py
torchcross/utils/layers.py
torchcross/utils/loops.py
torchcross-0.0.6.dist-info/METADATA
torchcross-0.0.6.dist-info/WHEEL
torchcross-0.0.6.dist-info/licenses/LICENSE
torchcross-0.0.6.dist-info/licenses/LICENSE.LESSER
torchcross-0.0.6.dist-info/RECORD
