Metadata-Version: 2.1
Name: torchcross
Version: 0.0.6
Summary: Easy-to-use PyTorch library for cross-domain learning, few-shot learning and meta-learning
Project-URL: Homepage, https://github.com/StefanoWoerner/torchcross
Project-URL: Issue Tracker, https://github.com/StefanoWoerner/torchcross/issues
Author-email: Stefano Woerner <stefano@woerner.eu>
License-File: LICENSE
License-File: LICENSE.LESSER
Classifier: Intended Audience :: Developers
Classifier: Intended Audience :: Education
Classifier: Intended Audience :: Science/Research
Classifier: License :: OSI Approved :: GNU Lesser General Public License v3 (LGPLv3)
Classifier: Operating System :: OS Independent
Classifier: Programming Language :: Python :: 3
Classifier: Programming Language :: Python :: 3.10
Classifier: Programming Language :: Python :: 3.11
Classifier: Topic :: Scientific/Engineering
Classifier: Topic :: Scientific/Engineering :: Artificial Intelligence
Requires-Python: >=3.10
Requires-Dist: lightning>=2.0.2
Requires-Dist: numpy>=1.24.3
Requires-Dist: omegaconf>=2.3.0
Requires-Dist: torch>=2.0.0
Requires-Dist: torchmetrics>=1.2.0
Requires-Dist: torchopt>=0.7.1
